fastinference_pytorch/__init__.py
fastinference_pytorch/_nbdev.py
fastinference_pytorch/tabular.py
fastinference_pytorch-0.0.2.dist-info/LICENSE
fastinference_pytorch-0.0.2.dist-info/METADATA
fastinference_pytorch-0.0.2.dist-info/WHEEL
fastinference_pytorch-0.0.2.dist-info/entry_points.txt
fastinference_pytorch-0.0.2.dist-info/top_level.txt
fastinference_pytorch-0.0.2.dist-info/RECORD
